<?xml version="1.0" encoding="UTF-8"?>
<list xmlns:xsi="http://www.w3.org/2001/XMLSchema-instance" xsi:noNamespaceSchemaLocation="../../xsd/items.xsd">
	<item id="33700" name="미확인의 드래곤 슬레이어" additionalName="이벤트" type="EtcItem">
		<set name="icon" val="icon.weapon_dragon_slayer_i00" />
		<set name="is_sellable" val="false" />
		<set name="crystal_type" val="A" />
		<set name="commissionItemType" val="TWO_HAND_SWORD" />
		<set name="default_action" val="SKILL_REDUCE_ON_SKILL_SUCCESS" />
		<set name="handler" val="ItemSkills" />
		<set name="material" val="FISH" />
		<skills>
			<skill id="12985" level="1" /> 
		</skills>
	</item>
	<item id="33701" name="미확인의 영혼의 활" additionalName="이벤트" type="EtcItem">
		<set name="icon" val="icon.weapon_soul_bow_i00" />
		<set name="is_sellable" val="false" />
		<set name="crystal_type" val="A" />
		<set name="commissionItemType" val="BOW" />
		<set name="default_action" val="SKILL_REDUCE_ON_SKILL_SUCCESS" />
		<set name="handler" val="ItemSkills" />
		<set name="material" val="FISH" />
		<skills>
			<skill id="12986" level="1" /> 
		</skills>
	</item>
	<item id="33702" name="미확인의 엘리시온" additionalName="이벤트" type="EtcItem">
		<set name="icon" val="icon.weapon_elysian_i00" />
		<set name="is_sellable" val="false" />
		<set name="crystal_type" val="A" />
		<set name="commissionItemType" val="BLUNT_WEAPON" />
		<set name="default_action" val="SKILL_REDUCE_ON_SKILL_SUCCESS" />
		<set name="handler" val="ItemSkills" />
		<set name="material" val="FISH" />
		<skills>
			<skill id="12987" level="1" /> 
		</skills>
	</item>
	<item id="33703" name="미확인의 드래곤 플레임 헤드" additionalName="이벤트" type="EtcItem">
		<set name="icon" val="icon.weapon_dragon_flame_head_i00" />
		<set name="is_sellable" val="false" />
		<set name="crystal_type" val="A" />
		<set name="commissionItemType" val="ONE_HAND_MAGIC_BLUNT_WEAPON" />
		<set name="default_action" val="SKILL_REDUCE_ON_SKILL_SUCCESS" />
		<set name="handler" val="ItemSkills" />
		<set name="material" val="FISH" />
		<skills>
			<skill id="12988" level="1" /> 
		</skills>
	</item>
	<item id="33704" name="미확인의 세계수의 가지" additionalName="이벤트" type="EtcItem">
		<set name="icon" val="icon.weapon_worldtrees_branch_i00" />
		<set name="is_sellable" val="false" />
		<set name="crystal_type" val="A" />
		<set name="commissionItemType" val="TWO_HAND_MAGIC_BLUNT_WEAPON" />
		<set name="default_action" val="SKILL_REDUCE_ON_SKILL_SUCCESS" />
		<set name="handler" val="ItemSkills" />
		<set name="material" val="FISH" />
		<skills>
			<skill id="12989" level="1" /> 
		</skills>
	</item>
	<item id="33705" name="미확인의 둠 크러셔" additionalName="이벤트" type="EtcItem">
		<set name="icon" val="icon.weapon_doom_crusher_i00" />
		<set name="is_sellable" val="false" />
		<set name="crystal_type" val="A" />
		<set name="commissionItemType" val="TWO_HAND_BLUNT_WEAPON" />
		<set name="default_action" val="SKILL_REDUCE_ON_SKILL_SUCCESS" />
		<set name="handler" val="ItemSkills" />
		<set name="material" val="FISH" />
		<skills>
			<skill id="12990" level="1" /> 
		</skills>
	</item>
	<item id="33706" name="미확인의 탈룸 글레이브" additionalName="이벤트" type="EtcItem">
		<set name="icon" val="icon.weapon_tallum_glaive_i00" />
		<set name="is_sellable" val="false" />
		<set name="crystal_type" val="A" />
		<set name="commissionItemType" val="SPEAR" />
		<set name="default_action" val="SKILL_REDUCE_ON_SKILL_SUCCESS" />
		<set name="handler" val="ItemSkills" />
		<set name="material" val="FISH" />
		<skills>
			<skill id="12991" level="1" /> 
		</skills>
	</item>
	<item id="33707" name="미확인의 드래곤 그라인더" additionalName="이벤트" type="EtcItem">
		<set name="icon" val="icon.weapon_dragon_grinder_i00" />
		<set name="is_sellable" val="false" />
		<set name="crystal_type" val="A" />
		<set name="commissionItemType" val="FIST_WEAPON" />
		<set name="default_action" val="SKILL_REDUCE_ON_SKILL_SUCCESS" />
		<set name="handler" val="ItemSkills" />
		<set name="material" val="FISH" />
		<skills>
			<skill id="12992" level="1" /> 
		</skills>
	</item>
	<item id="33708" name="미확인의 탈룸 블레이드*다마스커스" additionalName="이벤트" type="EtcItem">
		<set name="icon" val="icon.weapon_dual_sword_i00" />
		<set name="is_sellable" val="false" />
		<set name="crystal_type" val="A" />
		<set name="commissionItemType" val="DUALSWORD" />
		<set name="default_action" val="SKILL_REDUCE_ON_SKILL_SUCCESS" />
		<set name="handler" val="ItemSkills" />
		<set name="material" val="FISH" />
		<skills>
			<skill id="12933" level="1" /> 
		</skills>
	</item>
	<item id="33709" name="미확인의 악몽의 투구" additionalName="이벤트" type="EtcItem">
		<set name="icon" val="icon.armor_leather_helmet_i00" />
		<set name="is_sellable" val="false" />
		<set name="crystal_type" val="A" />
		<set name="commissionItemType" val="HELMET" />
		<set name="default_action" val="SKILL_REDUCE_ON_SKILL_SUCCESS" />
		<set name="handler" val="ItemSkills" />
		<set name="material" val="FISH" />
		<skills>
			<skill id="12993" level="1" /> 
		</skills>
	</item>
	<item id="33710" name="미확인의 악몽의 실드" additionalName="이벤트" type="EtcItem">
		<set name="icon" val="icon.shield_shield_of_nightmare_i00" />
		<set name="is_sellable" val="false" />
		<set name="crystal_type" val="A" />
		<set name="commissionItemType" val="SHIELD" />
		<set name="default_action" val="SKILL_REDUCE_ON_SKILL_SUCCESS" />
		<set name="handler" val="ItemSkills" />
		<set name="material" val="FISH" />
		<skills>
			<skill id="12994" level="1" /> 
		</skills>
	</item>
	<item id="33711" name="미확인의 악몽의 부츠" additionalName="이벤트" type="EtcItem">
		<set name="icon" val="icon.armor_t80_b_i02" />
		<set name="is_sellable" val="false" />
		<set name="crystal_type" val="A" />
		<set name="commissionItemType" val="FEET" />
		<set name="default_action" val="SKILL_REDUCE_ON_SKILL_SUCCESS" />
		<set name="handler" val="ItemSkills" />
		<set name="material" val="FISH" />
		<skills>
			<skill id="12995" level="1" /> 
		</skills>
	</item>
	<item id="33712" name="미확인의 악몽의 로브" additionalName="이벤트" type="EtcItem">
		<set name="icon" val="icon.armor_t82_ul_i00" />
		<set name="is_sellable" val="false" />
		<set name="crystal_type" val="A" />
		<set name="commissionItemType" val="FULL_BODY" />
		<set name="default_action" val="SKILL_REDUCE_ON_SKILL_SUCCESS" />
		<set name="handler" val="ItemSkills" />
		<set name="material" val="FISH" />
		<skills>
			<skill id="12996" level="1" /> 
		</skills>
	</item>
	<item id="33713" name="미확인의 악몽의 레더 메일" additionalName="이벤트" type="EtcItem">
		<set name="icon" val="icon.armor_t81_ul_i00" />
		<set name="is_sellable" val="false" />
		<set name="crystal_type" val="A" />
		<set name="commissionItemType" val="FULL_BODY" />
		<set name="default_action" val="SKILL_REDUCE_ON_SKILL_SUCCESS" />
		<set name="handler" val="ItemSkills" />
		<set name="material" val="FISH" />
		<skills>
			<skill id="12997" level="1" /> 
		</skills>
	</item>
	<item id="33714" name="미확인의 악몽의 건틀렛" additionalName="이벤트" type="EtcItem">
		<set name="icon" val="icon.armor_t80_g_i02" />
		<set name="is_sellable" val="false" />
		<set name="crystal_type" val="A" />
		<set name="commissionItemType" val="GLOVES" />
		<set name="default_action" val="SKILL_REDUCE_ON_SKILL_SUCCESS" />
		<set name="handler" val="ItemSkills" />
		<set name="material" val="FISH" />
		<skills>
			<skill id="12998" level="1" /> 
		</skills>
	</item>
	<item id="33715" name="미확인의 악몽의 갑옷" additionalName="이벤트" type="EtcItem">
		<set name="icon" val="icon.armor_t80_ul_i00" />
		<set name="is_sellable" val="false" />
		<set name="crystal_type" val="A" />
		<set name="commissionItemType" val="FULL_BODY" />
		<set name="default_action" val="SKILL_REDUCE_ON_SKILL_SUCCESS" />
		<set name="handler" val="ItemSkills" />
		<set name="material" val="FISH" />
		<skills>
			<skill id="12999" level="1" /> 
		</skills>
	</item>
	<item id="33716" name="미확인의 다이너스티 보우" additionalName="이벤트" type="EtcItem">
		<set name="icon" val="icon.weapon_dynasty_bow_i00" />
		<set name="is_sellable" val="false" />
		<set name="crystal_type" val="S" />
		<set name="commissionItemType" val="BOW" />
		<set name="default_action" val="SKILL_REDUCE_ON_SKILL_SUCCESS" />
		<set name="handler" val="ItemSkills" />
		<set name="material" val="FISH" />
		<skills>
			<skill id="12934" level="1" /> 
		</skills>
	</item>
	<item id="33717" name="듀얼리스트의 힘이 봉인된 듀얼소드" type="Weapon">
		<set name="icon" val="icon.weapon_r_dualsword_i00" />
		<set name="weapon_type" val="DUAL" />
		<set name="is_tradable" val="false" />
		<set name="is_dropable" val="false" />
		<set name="is_destroyable" val="false" />
		<set name="is_sellable" val="false" />
		<set name="soulshots" val="6" />
		<set name="spiritshots" val="6" />
		<set name="bodypart" val="lrhand" />
		<set name="is_oly_restricted" val="true" />
		<set name="damage_range" val="0;0;44;120" />
		<set name="immediate_effect" val="true" />
		<set name="default_action" val="EQUIP" />
		<set name="material" val="FINE_STEEL" />
		<stats>
			<stat type="pAtk">30</stat>
			<stat type="mAtk">30</stat>
			<stat type="pAtkSpd">325</stat>
			<stat type="rCrit">8</stat>
			<stat type="randomDamage">10</stat>
			<stat type="pAtkRange">40</stat>
		</stats>
	</item>
	<item id="33718" name="드레드노트의 힘이 봉인된 스피어" type="Weapon">
		<set name="icon" val="icon.weapon_eigelus_i00" />
		<set name="weapon_type" val="POLE" />
		<set name="is_tradable" val="false" />
		<set name="is_dropable" val="false" />
		<set name="is_destroyable" val="false" />
		<set name="is_sellable" val="false" />
		<set name="soulshots" val="6" />
		<set name="spiritshots" val="6" />
		<set name="bodypart" val="lrhand" />
		<set name="is_oly_restricted" val="true" />
		<set name="damage_range" val="0;0;66;120" />
		<set name="immediate_effect" val="true" />
		<set name="default_action" val="EQUIP" />
		<set name="material" val="STEEL" />
		<skills>
			<skill id="3599" level="1" /> 
		</skills>
		<stats>
			<stat type="pAtk">30</stat>
			<stat type="mAtk">30</stat>
			<stat type="rCrit">8</stat>
			<stat type="accCombat">-3.75</stat>
			<stat type="pAtkSpd">325</stat>
			<stat type="randomDamage">10</stat>
			<stat type="pAtkRange">100</stat>
		</stats>
	</item>
	<item id="33719" name="피닉스나이트의 힘이 봉인된 소드" type="Weapon">
		<set name="icon" val="icon.weapon_aseldor_i00" />
		<set name="weapon_type" val="SWORD" />
		<set name="is_tradable" val="false" />
		<set name="is_dropable" val="false" />
		<set name="is_destroyable" val="false" />
		<set name="is_sellable" val="false" />
		<set name="soulshots" val="6" />
		<set name="spiritshots" val="6" />
		<set name="bodypart" val="rhand" />
		<set name="is_oly_restricted" val="true" />
		<set name="damage_range" val="0;0;40;120" />
		<set name="immediate_effect" val="true" />
		<set name="default_action" val="EQUIP" />
		<set name="material" val="STEEL" />
		<stats>
			<stat type="pAtk">30</stat>
			<stat type="mAtk">30</stat>
			<stat type="pAtkSpd">379</stat>
			<stat type="rCrit">8</stat>
			<stat type="randomDamage">10</stat>
			<stat type="pAtkRange">40</stat>
		</stats>
	</item>
	<item id="33720" name="헬나이트의 힘이 봉인된 소드" type="Weapon">
		<set name="icon" val="icon.weapon_aseldor_i00" />
		<set name="weapon_type" val="SWORD" />
		<set name="is_tradable" val="false" />
		<set name="is_dropable" val="false" />
		<set name="is_destroyable" val="false" />
		<set name="is_sellable" val="false" />
		<set name="soulshots" val="6" />
		<set name="spiritshots" val="6" />
		<set name="bodypart" val="rhand" />
		<set name="is_oly_restricted" val="true" />
		<set name="damage_range" val="0;0;40;120" />
		<set name="immediate_effect" val="true" />
		<set name="default_action" val="EQUIP" />
		<set name="material" val="STEEL" />
		<stats>
			<stat type="pAtk">30</stat>
			<stat type="mAtk">30</stat>
			<stat type="pAtkSpd">379</stat>
			<stat type="rCrit">8</stat>
			<stat type="randomDamage">10</stat>
			<stat type="pAtkRange">40</stat>
		</stats>
	</item>
	<item id="33721" name="사지타리우스의 힘이 봉인된 보우" type="Weapon">
		<set name="icon" val="icon.weapon_karupis_i00" />
		<set name="weapon_type" val="BOW" />
		<set name="is_tradable" val="false" />
		<set name="is_dropable" val="false" />
		<set name="is_destroyable" val="false" />
		<set name="is_sellable" val="false" />
		<set name="soulshots" val="6" />
		<set name="spiritshots" val="6" />
		<set name="reuse_delay" val="1500" />
		<set name="bodypart" val="lrhand" />
		<set name="is_oly_restricted" val="true" />
		<set name="damage_range" val="0;0;10;0" />
		<set name="immediate_effect" val="true" />
		<set name="default_action" val="EQUIP" />
		<set name="material" val="WOOD" />
		<set name="mp_consume" val="1" />
		<stats>
			<stat type="pAtk">30</stat>
			<stat type="mAtk">30</stat>
			<stat type="pAtkSpd">293</stat>
			<stat type="rCrit">12</stat>
			<stat type="randomDamage">5</stat>
			<stat type="accCombat">-3.75</stat>
			<stat type="pAtkRange">500</stat>
		</stats>
	</item>
	<item id="33722" name="어드벤쳐러의 힘이 봉인된 듀얼대거" type="Weapon">
		<set name="icon" val="icon.weapon_r_dualdagger_i00" />
		<set name="weapon_type" val="DUALDAGGER" />
		<set name="is_tradable" val="false" />
		<set name="is_dropable" val="false" />
		<set name="is_destroyable" val="false" />
		<set name="is_sellable" val="false" />
		<set name="soulshots" val="6" />
		<set name="spiritshots" val="6" />
		<set name="bodypart" val="lrhand" />
		<set name="is_oly_restricted" val="true" />
		<set name="damage_range" val="0;0;44;120" />
		<set name="immediate_effect" val="true" />
		<set name="default_action" val="EQUIP" />
		<set name="material" val="STEEL" />
		<stats>
			<stat type="pAtk">30</stat>
			<stat type="mAtk">30</stat>
			<stat type="pAtkSpd">433</stat>
			<stat type="rCrit">12</stat>
			<stat type="randomDamage">10</stat>
			<stat type="accCombat">-3.75</stat>
			<stat type="pAtkRange">40</stat>
		</stats>
	</item>
	<item id="33723" name="아크메이지의 힘이 봉인된 소드" type="Weapon">
		<set name="icon" val="icon.weapon_terakan_i00" />
		<set name="weapon_type" val="SWORD" />
		<set name="is_tradable" val="false" />
		<set name="is_dropable" val="false" />
		<set name="is_destroyable" val="false" />
		<set name="is_sellable" val="false" />
		<set name="soulshots" val="6" />
		<set name="spiritshots" val="6" />
		<set name="bodypart" val="rhand" />
		<set name="is_oly_restricted" val="true" />
		<set name="damage_range" val="0;0;40;120" />
		<set name="immediate_effect" val="true" />
		<set name="default_action" val="EQUIP" />
		<set name="material" val="BRONZE" />
		<set name="is_magic_weapon" val="true" />
		<stats>
			<stat type="pAtk">30</stat>
			<stat type="mAtk">30</stat>
			<stat type="pAtkSpd">379</stat>
			<stat type="rCrit">8</stat>
			<stat type="randomDamage">10</stat>
			<stat type="pAtkRange">40</stat>
		</stats>
	</item>
	<item id="33724" name="소울테이커의 힘이 봉인된 소드" type="Weapon">
		<set name="icon" val="icon.weapon_terakan_i00" />
		<set name="weapon_type" val="SWORD" />
		<set name="is_tradable" val="false" />
		<set name="is_dropable" val="false" />
		<set name="is_destroyable" val="false" />
		<set name="is_sellable" val="false" />
		<set name="soulshots" val="6" />
		<set name="spiritshots" val="6" />
		<set name="bodypart" val="rhand" />
		<set name="is_oly_restricted" val="true" />
		<set name="damage_range" val="0;0;40;120" />
		<set name="immediate_effect" val="true" />
		<set name="default_action" val="EQUIP" />
		<set name="material" val="BRONZE" />
		<set name="is_magic_weapon" val="true" />
		<stats>
			<stat type="pAtk">30</stat>
			<stat type="mAtk">30</stat>
			<stat type="pAtkSpd">379</stat>
			<stat type="rCrit">8</stat>
			<stat type="randomDamage">10</stat>
			<stat type="pAtkRange">40</stat>
		</stats>
	</item>
	<item id="33725" name="아르카나로드의 힘이 봉인된 블런트" type="Weapon">
		<set name="icon" val="icon.weapon_kitz_i00" />
		<set name="weapon_type" val="BLUNT" />
		<set name="is_tradable" val="false" />
		<set name="is_dropable" val="false" />
		<set name="is_destroyable" val="false" />
		<set name="is_sellable" val="false" />
		<set name="soulshots" val="6" />
		<set name="spiritshots" val="6" />
		<set name="bodypart" val="rhand" />
		<set name="is_oly_restricted" val="true" />
		<set name="damage_range" val="0;0;40;120" />
		<set name="immediate_effect" val="true" />
		<set name="default_action" val="EQUIP" />
		<set name="material" val="WOOD" />
		<set name="is_magic_weapon" val="true" />
		<stats>
			<stat type="pAtk">30</stat>
			<stat type="mAtk">30</stat>
			<stat type="pAtkSpd">379</stat>
			<stat type="accCombat">8</stat>
			<stat type="rCrit">6</stat>
			<stat type="randomDamage">20</stat>
			<stat type="pAtkRange">40</stat>
		</stats>
	</item>
	<item id="33726" name="카디날의 힘이 봉인된 스태프" type="Weapon">
		<set name="icon" val="icon.weapon_arcorda_i00" />
		<set name="weapon_type" val="BLUNT" />
		<set name="is_tradable" val="false" />
		<set name="is_dropable" val="false" />
		<set name="is_destroyable" val="false" />
		<set name="is_sellable" val="false" />
		<set name="soulshots" val="6" />
		<set name="spiritshots" val="6" />
		<set name="bodypart" val="lrhand" />
		<set name="is_oly_restricted" val="true" />
		<set name="damage_range" val="0;0;46;120" />
		<set name="immediate_effect" val="true" />
		<set name="default_action" val="EQUIP" />
		<set name="material" val="CRYSTAL" />
		<set name="is_magic_weapon" val="true" />
		<stats>
			<stat type="pAtk">30</stat>
			<stat type="mAtk">30</stat>
			<stat type="pAtkSpd">325</stat>
			<stat type="accCombat">8</stat>
			<stat type="rCrit">6</stat>
			<stat type="randomDamage">20</stat>
			<stat type="pAtkRange">40</stat>
		</stats>
	</item>
	<item id="33727" name="하이로펀트의 힘이 봉인된 스태프" type="Weapon">
		<set name="icon" val="icon.weapon_arcorda_i00" />
		<set name="weapon_type" val="BLUNT" />
		<set name="is_tradable" val="false" />
		<set name="is_dropable" val="false" />
		<set name="is_destroyable" val="false" />
		<set name="is_sellable" val="false" />
		<set name="soulshots" val="6" />
		<set name="spiritshots" val="6" />
		<set name="bodypart" val="lrhand" />
		<set name="is_oly_restricted" val="true" />
		<set name="damage_range" val="0;0;46;120" />
		<set name="immediate_effect" val="true" />
		<set name="default_action" val="EQUIP" />
		<set name="material" val="CRYSTAL" />
		<set name="is_magic_weapon" val="true" />
		<stats>
			<stat type="pAtk">30</stat>
			<stat type="mAtk">30</stat>
			<stat type="pAtkSpd">325</stat>
			<stat type="accCombat">8</stat>
			<stat type="rCrit">6</stat>
			<stat type="randomDamage">20</stat>
			<stat type="pAtkRange">40</stat>
		</stats>
	</item>
	<item id="33728" name="에바스템플러의 힘이 봉인된 소드" type="Weapon">
		<set name="icon" val="icon.weapon_aseldor_i00" />
		<set name="weapon_type" val="SWORD" />
		<set name="is_tradable" val="false" />
		<set name="is_dropable" val="false" />
		<set name="is_destroyable" val="false" />
		<set name="is_sellable" val="false" />
		<set name="soulshots" val="6" />
		<set name="spiritshots" val="6" />
		<set name="bodypart" val="rhand" />
		<set name="is_oly_restricted" val="true" />
		<set name="damage_range" val="0;0;40;120" />
		<set name="immediate_effect" val="true" />
		<set name="default_action" val="EQUIP" />
		<set name="material" val="STEEL" />
		<stats>
			<stat type="pAtk">30</stat>
			<stat type="mAtk">30</stat>
			<stat type="pAtkSpd">379</stat>
			<stat type="rCrit">8</stat>
			<stat type="randomDamage">10</stat>
			<stat type="pAtkRange">40</stat>
		</stats>
	</item>
	<item id="33729" name="소드뮤즈의 힘이 봉인된 소드" type="Weapon">
		<set name="icon" val="icon.weapon_aseldor_i00" />
		<set name="weapon_type" val="SWORD" />
		<set name="is_tradable" val="false" />
		<set name="is_dropable" val="false" />
		<set name="is_destroyable" val="false" />
		<set name="is_sellable" val="false" />
		<set name="soulshots" val="6" />
		<set name="spiritshots" val="6" />
		<set name="bodypart" val="rhand" />
		<set name="is_oly_restricted" val="true" />
		<set name="damage_range" val="0;0;40;120" />
		<set name="immediate_effect" val="true" />
		<set name="default_action" val="EQUIP" />
		<set name="material" val="STEEL" />
		<stats>
			<stat type="pAtk">30</stat>
			<stat type="mAtk">30</stat>
			<stat type="pAtkSpd">379</stat>
			<stat type="rCrit">8</stat>
			<stat type="randomDamage">10</stat>
			<stat type="pAtkRange">40</stat>
		</stats>
	</item>
	<item id="33730" name="윈드라이더의 힘이 봉인된 대거" type="Weapon">
		<set name="icon" val="icon.weapon_radice_i00" />
		<set name="weapon_type" val="DAGGER" />
		<set name="is_tradable" val="false" />
		<set name="is_dropable" val="false" />
		<set name="is_destroyable" val="false" />
		<set name="is_sellable" val="false" />
		<set name="soulshots" val="6" />
		<set name="spiritshots" val="6" />
		<set name="bodypart" val="rhand" />
		<set name="is_oly_restricted" val="true" />
		<set name="damage_range" val="0;0;40;120" />
		<set name="immediate_effect" val="true" />
		<set name="default_action" val="EQUIP" />
		<set name="material" val="STEEL" />
		<stats>
			<stat type="pAtk">30</stat>
			<stat type="mAtk">30</stat>
			<stat type="pAtkSpd">433</stat>
			<stat type="rCrit">12</stat>
			<stat type="randomDamage">5</stat>
			<stat type="accCombat">-3.75</stat>
			<stat type="pAtkRange">40</stat>
		</stats>
	</item>
	<item id="33731" name="문라이트센티넬의 힘이 봉인된 보우" type="Weapon">
		<set name="icon" val="icon.weapon_karupis_i00" />
		<set name="weapon_type" val="BOW" />
		<set name="is_tradable" val="false" />
		<set name="is_dropable" val="false" />
		<set name="is_destroyable" val="false" />
		<set name="is_sellable" val="false" />
		<set name="soulshots" val="6" />
		<set name="spiritshots" val="6" />
		<set name="reuse_delay" val="1500" />
		<set name="bodypart" val="lrhand" />
		<set name="is_oly_restricted" val="true" />
		<set name="damage_range" val="0;0;10;0" />
		<set name="immediate_effect" val="true" />
		<set name="default_action" val="EQUIP" />
		<set name="material" val="WOOD" />
		<set name="mp_consume" val="1" />
		<stats>
			<stat type="pAtk">30</stat>
			<stat type="mAtk">30</stat>
			<stat type="pAtkSpd">293</stat>
			<stat type="rCrit">12</stat>
			<stat type="randomDamage">5</stat>
			<stat type="accCombat">-3.75</stat>
			<stat type="pAtkRange">500</stat>
		</stats>
	</item>
	<item id="33732" name="미스틱뮤즈의 힘이 봉인된 소드" type="Weapon">
		<set name="icon" val="icon.weapon_terakan_i00" />
		<set name="weapon_type" val="SWORD" />
		<set name="is_tradable" val="false" />
		<set name="is_dropable" val="false" />
		<set name="is_destroyable" val="false" />
		<set name="is_sellable" val="false" />
		<set name="soulshots" val="6" />
		<set name="spiritshots" val="6" />
		<set name="bodypart" val="rhand" />
		<set name="is_oly_restricted" val="true" />
		<set name="damage_range" val="0;0;40;120" />
		<set name="immediate_effect" val="true" />
		<set name="default_action" val="EQUIP" />
		<set name="material" val="BRONZE" />
		<set name="is_magic_weapon" val="true" />
		<stats>
			<stat type="pAtk">30</stat>
			<stat type="mAtk">30</stat>
			<stat type="pAtkSpd">379</stat>
			<stat type="rCrit">8</stat>
			<stat type="randomDamage">10</stat>
			<stat type="pAtkRange">40</stat>
		</stats>
	</item>
	<item id="33733" name="엘레멘탈마스터의 힘이 봉인된 블런트" type="Weapon">
		<set name="icon" val="icon.weapon_kitz_i00" />
		<set name="weapon_type" val="BLUNT" />
		<set name="is_tradable" val="false" />
		<set name="is_dropable" val="false" />
		<set name="is_destroyable" val="false" />
		<set name="is_sellable" val="false" />
		<set name="soulshots" val="6" />
		<set name="spiritshots" val="6" />
		<set name="bodypart" val="rhand" />
		<set name="is_oly_restricted" val="true" />
		<set name="damage_range" val="0;0;40;120" />
		<set name="immediate_effect" val="true" />
		<set name="default_action" val="EQUIP" />
		<set name="material" val="WOOD" />
		<set name="is_magic_weapon" val="true" />
		<stats>
			<stat type="pAtk">30</stat>
			<stat type="mAtk">30</stat>
			<stat type="pAtkSpd">379</stat>
			<stat type="accCombat">8</stat>
			<stat type="rCrit">6</stat>
			<stat type="randomDamage">20</stat>
			<stat type="pAtkRange">40</stat>
		</stats>
	</item>
	<item id="33734" name="에바스세인트의 힘이 봉인된 블런트" type="Weapon">
		<set name="icon" val="icon.weapon_kitz_i00" />
		<set name="weapon_type" val="BLUNT" />
		<set name="is_tradable" val="false" />
		<set name="is_dropable" val="false" />
		<set name="is_destroyable" val="false" />
		<set name="is_sellable" val="false" />
		<set name="soulshots" val="6" />
		<set name="spiritshots" val="6" />
		<set name="bodypart" val="rhand" />
		<set name="is_oly_restricted" val="true" />
		<set name="damage_range" val="0;0;40;120" />
		<set name="immediate_effect" val="true" />
		<set name="default_action" val="EQUIP" />
		<set name="material" val="WOOD" />
		<set name="is_magic_weapon" val="true" />
		<stats>
			<stat type="pAtk">30</stat>
			<stat type="mAtk">30</stat>
			<stat type="pAtkSpd">379</stat>
			<stat type="accCombat">8</stat>
			<stat type="rCrit">6</stat>
			<stat type="randomDamage">20</stat>
			<stat type="pAtkRange">40</stat>
		</stats>
	</item>
	<item id="33735" name="실리엔템플러의 힘이 봉인된 소드" type="Weapon">
		<set name="icon" val="icon.weapon_aseldor_i00" />
		<set name="weapon_type" val="SWORD" />
		<set name="is_tradable" val="false" />
		<set name="is_dropable" val="false" />
		<set name="is_destroyable" val="false" />
		<set name="is_sellable" val="false" />
		<set name="soulshots" val="6" />
		<set name="spiritshots" val="6" />
		<set name="bodypart" val="rhand" />
		<set name="is_oly_restricted" val="true" />
		<set name="damage_range" val="0;0;40;120" />
		<set name="immediate_effect" val="true" />
		<set name="default_action" val="EQUIP" />
		<set name="material" val="STEEL" />
		<stats>
			<stat type="pAtk">30</stat>
			<stat type="mAtk">30</stat>
			<stat type="pAtkSpd">379</stat>
			<stat type="rCrit">8</stat>
			<stat type="randomDamage">10</stat>
			<stat type="pAtkRange">40</stat>
		</stats>
	</item>
	<item id="33736" name="스펙트럴댄서의 힘이 봉인된 듀얼소드" type="Weapon">
		<set name="icon" val="icon.weapon_r_dualsword_i00" />
		<set name="weapon_type" val="DUAL" />
		<set name="is_tradable" val="false" />
		<set name="is_dropable" val="false" />
		<set name="is_destroyable" val="false" />
		<set name="is_sellable" val="false" />
		<set name="soulshots" val="6" />
		<set name="spiritshots" val="6" />
		<set name="bodypart" val="lrhand" />
		<set name="is_oly_restricted" val="true" />
		<set name="damage_range" val="0;0;44;120" />
		<set name="immediate_effect" val="true" />
		<set name="default_action" val="EQUIP" />
		<set name="material" val="FINE_STEEL" />
		<stats>
			<stat type="pAtk">30</stat>
			<stat type="mAtk">30</stat>
			<stat type="pAtkSpd">325</stat>
			<stat type="rCrit">8</stat>
			<stat type="randomDamage">10</stat>
			<stat type="pAtkRange">40</stat>
		</stats>
	</item>
	<item id="33737" name="고스트헌터의 힘이 봉인된 대거" type="Weapon">
		<set name="icon" val="icon.weapon_radice_i00" />
		<set name="weapon_type" val="DAGGER" />
		<set name="is_tradable" val="false" />
		<set name="is_dropable" val="false" />
		<set name="is_destroyable" val="false" />
		<set name="is_sellable" val="false" />
		<set name="soulshots" val="6" />
		<set name="spiritshots" val="6" />
		<set name="bodypart" val="rhand" />
		<set name="is_oly_restricted" val="true" />
		<set name="damage_range" val="0;0;40;120" />
		<set name="immediate_effect" val="true" />
		<set name="default_action" val="EQUIP" />
		<set name="material" val="STEEL" />
		<stats>
			<stat type="pAtk">30</stat>
			<stat type="mAtk">30</stat>
			<stat type="pAtkSpd">433</stat>
			<stat type="rCrit">12</stat>
			<stat type="randomDamage">5</stat>
			<stat type="accCombat">-3.75</stat>
			<stat type="pAtkRange">40</stat>
		</stats>
	</item>
	<item id="33738" name="고스트센티넬의 힘이 봉인된 보우" type="Weapon">
		<set name="icon" val="icon.weapon_karupis_i00" />
		<set name="weapon_type" val="BOW" />
		<set name="is_tradable" val="false" />
		<set name="is_dropable" val="false" />
		<set name="is_destroyable" val="false" />
		<set name="is_sellable" val="false" />
		<set name="soulshots" val="6" />
		<set name="spiritshots" val="6" />
		<set name="reuse_delay" val="1500" />
		<set name="bodypart" val="lrhand" />
		<set name="is_oly_restricted" val="true" />
		<set name="damage_range" val="0;0;10;0" />
		<set name="immediate_effect" val="true" />
		<set name="default_action" val="EQUIP" />
		<set name="material" val="WOOD" />
		<set name="mp_consume" val="1" />
		<stats>
			<stat type="pAtk">30</stat>
			<stat type="mAtk">30</stat>
			<stat type="pAtkSpd">293</stat>
			<stat type="rCrit">12</stat>
			<stat type="randomDamage">5</stat>
			<stat type="accCombat">-3.75</stat>
			<stat type="pAtkRange">500</stat>
		</stats>
	</item>
	<item id="33739" name="스톰스크리머의 힘이 봉인된 소드" type="Weapon">
		<set name="icon" val="icon.weapon_terakan_i00" />
		<set name="weapon_type" val="SWORD" />
		<set name="is_tradable" val="false" />
		<set name="is_dropable" val="false" />
		<set name="is_destroyable" val="false" />
		<set name="is_sellable" val="false" />
		<set name="soulshots" val="6" />
		<set name="spiritshots" val="6" />
		<set name="bodypart" val="rhand" />
		<set name="is_oly_restricted" val="true" />
		<set name="damage_range" val="0;0;40;120" />
		<set name="immediate_effect" val="true" />
		<set name="default_action" val="EQUIP" />
		<set name="material" val="BRONZE" />
		<set name="is_magic_weapon" val="true" />
		<stats>
			<stat type="pAtk">30</stat>
			<stat type="mAtk">30</stat>
			<stat type="pAtkSpd">379</stat>
			<stat type="rCrit">8</stat>
			<stat type="randomDamage">10</stat>
			<stat type="pAtkRange">40</stat>
		</stats>
	</item>
	<item id="33740" name="스펙트럴마스터의 힘이 봉인된 소드" type="Weapon">
		<set name="icon" val="icon.weapon_terakan_i00" />
		<set name="weapon_type" val="SWORD" />
		<set name="is_tradable" val="false" />
		<set name="is_dropable" val="false" />
		<set name="is_destroyable" val="false" />
		<set name="is_sellable" val="false" />
		<set name="soulshots" val="6" />
		<set name="spiritshots" val="6" />
		<set name="bodypart" val="rhand" />
		<set name="is_oly_restricted" val="true" />
		<set name="damage_range" val="0;0;40;120" />
		<set name="immediate_effect" val="true" />
		<set name="default_action" val="EQUIP" />
		<set name="material" val="BRONZE" />
		<set name="is_magic_weapon" val="true" />
		<stats>
			<stat type="pAtk">30</stat>
			<stat type="mAtk">30</stat>
			<stat type="pAtkSpd">379</stat>
			<stat type="rCrit">8</stat>
			<stat type="randomDamage">10</stat>
			<stat type="pAtkRange">40</stat>
		</stats>
	</item>
	<item id="33741" name="실리엔세인트의 힘이 봉인된 블런트" type="Weapon">
		<set name="icon" val="icon.weapon_kitz_i00" />
		<set name="weapon_type" val="BLUNT" />
		<set name="is_tradable" val="false" />
		<set name="is_dropable" val="false" />
		<set name="is_destroyable" val="false" />
		<set name="is_sellable" val="false" />
		<set name="soulshots" val="6" />
		<set name="spiritshots" val="6" />
		<set name="bodypart" val="rhand" />
		<set name="is_oly_restricted" val="true" />
		<set name="damage_range" val="0;0;40;120" />
		<set name="immediate_effect" val="true" />
		<set name="default_action" val="EQUIP" />
		<set name="material" val="WOOD" />
		<set name="is_magic_weapon" val="true" />
		<stats>
			<stat type="pAtk">30</stat>
			<stat type="mAtk">30</stat>
			<stat type="pAtkSpd">379</stat>
			<stat type="accCombat">8</stat>
			<stat type="rCrit">6</stat>
			<stat type="randomDamage">20</stat>
			<stat type="pAtkRange">40</stat>
		</stats>
	</item>
	<item id="33742" name="타이탄의 힘이 봉인된 투핸드소드" type="Weapon">
		<set name="icon" val="icon.weapon_spigel_i00" />
		<set name="weapon_type" val="SWORD" />
		<set name="is_tradable" val="false" />
		<set name="is_dropable" val="false" />
		<set name="is_destroyable" val="false" />
		<set name="is_sellable" val="false" />
		<set name="soulshots" val="6" />
		<set name="spiritshots" val="6" />
		<set name="bodypart" val="lrhand" />
		<set name="is_oly_restricted" val="true" />
		<set name="damage_range" val="0;0;40;120" />
		<set name="immediate_effect" val="true" />
		<set name="default_action" val="EQUIP" />
		<set name="material" val="STEEL" />
		<stats>
			<stat type="pAtk">30</stat>
			<stat type="mAtk">30</stat>
			<stat type="pAtkSpd">325</stat>
			<stat type="rCrit">8</stat>
			<stat type="randomDamage">10</stat>
			<stat type="pAtkRange">40</stat>
		</stats>
	</item>
	<item id="33743" name="그랜드카바타리의 힘이 봉인된 듀얼피스트" type="Weapon">
		<set name="icon" val="icon.weapon_fantasma_i00" />
		<set name="weapon_type" val="DUALFIST" />
		<set name="is_tradable" val="false" />
		<set name="is_dropable" val="false" />
		<set name="is_destroyable" val="false" />
		<set name="is_sellable" val="false" />
		<set name="soulshots" val="6" />
		<set name="spiritshots" val="6" />
		<set name="bodypart" val="lrhand" />
		<set name="is_oly_restricted" val="true" />
		<set name="damage_range" val="0;0;32;120" />
		<set name="immediate_effect" val="true" />
		<set name="default_action" val="EQUIP" />
		<set name="material" val="LEATHER" />
		<stats>
			<stat type="pAtk">30</stat>
			<stat type="mAtk">30</stat>
			<stat type="pAtkSpd">325</stat>
			<stat type="accCombat">8</stat>
			<stat type="rCrit">6</stat>
			<stat type="randomDamage">5</stat>
			<stat type="pAtkRange">40</stat>
		</stats>
	</item>
	<item id="33744" name="도미네이터의 힘이 봉인된 소드" type="Weapon">
		<set name="icon" val="icon.weapon_aseldor_i00" />
		<set name="weapon_type" val="SWORD" />
		<set name="is_tradable" val="false" />
		<set name="is_dropable" val="false" />
		<set name="is_destroyable" val="false" />
		<set name="is_sellable" val="false" />
		<set name="soulshots" val="6" />
		<set name="spiritshots" val="6" />
		<set name="bodypart" val="rhand" />
		<set name="is_oly_restricted" val="true" />
		<set name="damage_range" val="0;0;40;120" />
		<set name="immediate_effect" val="true" />
		<set name="default_action" val="EQUIP" />
		<set name="material" val="STEEL" />
		<stats>
			<stat type="pAtk">30</stat>
			<stat type="mAtk">30</stat>
			<stat type="pAtkSpd">379</stat>
			<stat type="rCrit">8</stat>
			<stat type="randomDamage">10</stat>
			<stat type="pAtkRange">40</stat>
		</stats>
	</item>
	<item id="33745" name="둠크라이어의 힘이 봉인된 듀얼소드" type="Weapon">
		<set name="icon" val="icon.weapon_r_dualsword_i00" />
		<set name="weapon_type" val="DUAL" />
		<set name="is_tradable" val="false" />
		<set name="is_dropable" val="false" />
		<set name="is_destroyable" val="false" />
		<set name="is_sellable" val="false" />
		<set name="soulshots" val="6" />
		<set name="spiritshots" val="6" />
		<set name="bodypart" val="lrhand" />
		<set name="is_oly_restricted" val="true" />
		<set name="damage_range" val="0;0;44;120" />
		<set name="immediate_effect" val="true" />
		<set name="default_action" val="EQUIP" />
		<set name="material" val="FINE_STEEL" />
		<stats>
			<stat type="pAtk">30</stat>
			<stat type="mAtk">30</stat>
			<stat type="pAtkSpd">325</stat>
			<stat type="rCrit">8</stat>
			<stat type="randomDamage">10</stat>
			<stat type="pAtkRange">40</stat>
		</stats>
	</item>
	<item id="33746" name="포츈시커의 힘이 봉인된 대거" type="Weapon">
		<set name="icon" val="icon.weapon_radice_i00" />
		<set name="weapon_type" val="DAGGER" />
		<set name="is_tradable" val="false" />
		<set name="is_dropable" val="false" />
		<set name="is_destroyable" val="false" />
		<set name="is_sellable" val="false" />
		<set name="soulshots" val="6" />
		<set name="spiritshots" val="6" />
		<set name="bodypart" val="rhand" />
		<set name="is_oly_restricted" val="true" />
		<set name="damage_range" val="0;0;40;120" />
		<set name="immediate_effect" val="true" />
		<set name="default_action" val="EQUIP" />
		<set name="material" val="STEEL" />
		<stats>
			<stat type="pAtk">30</stat>
			<stat type="mAtk">30</stat>
			<stat type="pAtkSpd">433</stat>
			<stat type="rCrit">12</stat>
			<stat type="randomDamage">5</stat>
			<stat type="accCombat">-3.75</stat>
			<stat type="pAtkRange">40</stat>
		</stats>
	</item>
	<item id="33747" name="마에스트로의 힘이 봉인된 스태프" type="Weapon">
		<set name="icon" val="icon.weapon_arcorda_i00" />
		<set name="weapon_type" val="BLUNT" />
		<set name="is_tradable" val="false" />
		<set name="is_dropable" val="false" />
		<set name="is_destroyable" val="false" />
		<set name="is_sellable" val="false" />
		<set name="soulshots" val="6" />
		<set name="spiritshots" val="6" />
		<set name="bodypart" val="lrhand" />
		<set name="is_oly_restricted" val="true" />
		<set name="damage_range" val="0;0;46;120" />
		<set name="immediate_effect" val="true" />
		<set name="default_action" val="EQUIP" />
		<set name="material" val="CRYSTAL" />
		<set name="is_magic_weapon" val="true" />
		<stats>
			<stat type="pAtk">30</stat>
			<stat type="mAtk">30</stat>
			<stat type="pAtkSpd">325</stat>
			<stat type="accCombat">8</stat>
			<stat type="rCrit">6</stat>
			<stat type="randomDamage">20</stat>
			<stat type="pAtkRange">40</stat>
		</stats>
	</item>
	<item id="33748" name="작은 쿠쿠린 주머니" type="EtcItem">
		<set name="icon" val="icon.etc_pouch_yellow_i00" />
		<set name="weight" val="100" />
		<set name="is_tradable" val="false" />
		<set name="is_dropable" val="false" />
		<set name="is_sellable" val="false" />
		<set name="is_oly_restricted" val="true" />
		<set name="is_freightable" val="true" />
		<set name="default_action" val="PEEL" />
		<set name="immediate_effect" val="true" />
		<set name="is_stackable" val="true" />
		<set name="handler" val="ExtractableItems" />
		<set name="material" val="FISH" />
		<capsuled_items>
			<item id="33649" min="1" max="1" chance="100" /> 
		</capsuled_items>
	</item>
	<item id="33749" name="큰 쿠쿠린 주머니" type="EtcItem">
		<set name="icon" val="icon.etc_pouch_yellow_i00" />
		<set name="weight" val="100" />
		<set name="is_tradable" val="false" />
		<set name="is_dropable" val="false" />
		<set name="is_sellable" val="false" />
		<set name="is_oly_restricted" val="true" />
		<set name="is_freightable" val="true" />
		<set name="default_action" val="PEEL" />
		<set name="immediate_effect" val="true" />
		<set name="is_stackable" val="true" />
		<set name="handler" val="ExtractableItems" />
		<set name="material" val="FISH" />
		<capsuled_items>
			<item id="33649" min="1" max="1" chance="100" /> 
			<item id="33642" min="1" max="1" chance="100" /> 
		</capsuled_items>
	</item>
	<item id="33750" name="테스트용 레퀴엠 무기 낡은것" type="Weapon">
		<set name="icon" val="icon.weapon_estia_i00" />
		<set name="default_action" val="EQUIP" />
		<set name="bodypart" val="rhand" />
		<set name="weapon_type" val="SWORD" />
		<set name="crystal_type" val="R" />
		<set name="crystal_count" val="2902" />
		<set name="weight" val="1520" />
		<set name="price" val="136041000" />
		<set name="soulshots" val="1" />
		<set name="spiritshots" val="1" />
		<set name="enchant_enabled" val="true" />
		<set name="element_enabled" val="true" />
		<set name="commissionItemType" val="ONE_HAND_SWORD" />
		<set name="isAppearanceable" val="true" />
		<set name="damage_range" val="0;0;40;120" />
		<set name="immediate_effect" val="true" />
		<set name="material" val="STEEL" />
		<skills>
			<skill id="13252" level="3" type="ON_ENCHANT" type_value="4" /> 
		</skills>
		<stats>
			<stat type="pAtk">489</stat>
			<stat type="mAtk">226</stat>
			<stat type="pAtkSpd">379</stat>
			<stat type="rCrit">8</stat>
			<stat type="randomDamage">10</stat>
			<stat type="pAtkRange">40</stat>
		</stats>
	</item>
	<item id="33751" name="테스트용 레퀴엠 무기 컬러베리" type="Weapon">
		<set name="icon" val="icon.weapon_estia_i00" />
		<set name="default_action" val="EQUIP" />
		<set name="bodypart" val="rhand" />
		<set name="weapon_type" val="SWORD" />
		<set name="crystal_type" val="R" />
		<set name="crystal_count" val="2902" />
		<set name="weight" val="1520" />
		<set name="price" val="136041000" />
		<set name="soulshots" val="1" />
		<set name="spiritshots" val="1" />
		<set name="enchant_enabled" val="true" />
		<set name="element_enabled" val="true" />
		<set name="commissionItemType" val="ONE_HAND_SWORD" />
		<set name="isAppearanceable" val="true" />
		<set name="damage_range" val="0;0;40;120" />
		<set name="immediate_effect" val="true" />
		<set name="material" val="STEEL" />
		<skills>
			<skill id="13252" level="3" type="ON_ENCHANT" type_value="4" /> 
		</skills>
		<stats>
			<stat type="pAtk">489</stat>
			<stat type="mAtk">226</stat>
			<stat type="pAtkSpd">379</stat>
			<stat type="rCrit">8</stat>
			<stat type="randomDamage">10</stat>
			<stat type="pAtkRange">40</stat>
		</stats>
	</item>
	<item id="33752" name="테스트용 아포 무기 낡은것" type="Weapon">
		<set name="icon" val="icon.weapon_estia_i00" />
		<set name="default_action" val="EQUIP" />
		<set name="bodypart" val="rhand" />
		<set name="weapon_type" val="SWORD" />
		<set name="crystal_type" val="R" />
		<set name="crystal_count" val="2902" />
		<set name="weight" val="1520" />
		<set name="price" val="136041000" />
		<set name="soulshots" val="1" />
		<set name="spiritshots" val="1" />
		<set name="enchant_enabled" val="true" />
		<set name="element_enabled" val="true" />
		<set name="commissionItemType" val="ONE_HAND_SWORD" />
		<set name="isAppearanceable" val="true" />
		<set name="damage_range" val="0;0;40;120" />
		<set name="immediate_effect" val="true" />
		<set name="material" val="STEEL" />
		<skills>
			<skill id="13252" level="3" type="ON_ENCHANT" type_value="4" /> 
		</skills>
		<stats>
			<stat type="pAtk">489</stat>
			<stat type="mAtk">226</stat>
			<stat type="pAtkSpd">379</stat>
			<stat type="rCrit">8</stat>
			<stat type="randomDamage">10</stat>
			<stat type="pAtkRange">40</stat>
		</stats>
	</item>
	<item id="33753" name="테스트용 아포 무기 컬러베리" type="Weapon">
		<set name="icon" val="icon.weapon_estia_i00" />
		<set name="default_action" val="EQUIP" />
		<set name="bodypart" val="rhand" />
		<set name="weapon_type" val="SWORD" />
		<set name="crystal_type" val="R" />
		<set name="crystal_count" val="2902" />
		<set name="weight" val="1520" />
		<set name="price" val="136041000" />
		<set name="soulshots" val="1" />
		<set name="spiritshots" val="1" />
		<set name="enchant_enabled" val="true" />
		<set name="element_enabled" val="true" />
		<set name="commissionItemType" val="ONE_HAND_SWORD" />
		<set name="isAppearanceable" val="true" />
		<set name="damage_range" val="0;0;40;120" />
		<set name="immediate_effect" val="true" />
		<set name="material" val="STEEL" />
		<skills>
			<skill id="13252" level="3" type="ON_ENCHANT" type_value="4" /> 
		</skills>
		<stats>
			<stat type="pAtk">489</stat>
			<stat type="mAtk">226</stat>
			<stat type="pAtkSpd">379</stat>
			<stat type="rCrit">8</stat>
			<stat type="randomDamage">10</stat>
			<stat type="pAtkRange">40</stat>
		</stats>
	</item>
	<item id="33754" name="테스트용 판타 무기 낡은것" type="Weapon">
		<set name="icon" val="icon.weapon_estia_i00" />
		<set name="default_action" val="EQUIP" />
		<set name="bodypart" val="rhand" />
		<set name="weapon_type" val="SWORD" />
		<set name="crystal_type" val="R" />
		<set name="crystal_count" val="2902" />
		<set name="weight" val="1520" />
		<set name="price" val="136041000" />
		<set name="soulshots" val="1" />
		<set name="spiritshots" val="1" />
		<set name="enchant_enabled" val="true" />
		<set name="element_enabled" val="true" />
		<set name="commissionItemType" val="ONE_HAND_SWORD" />
		<set name="isAppearanceable" val="true" />
		<set name="damage_range" val="0;0;40;120" />
		<set name="immediate_effect" val="true" />
		<set name="material" val="STEEL" />
		<skills>
			<skill id="13252" level="3" type="ON_ENCHANT" type_value="4" /> 
		</skills>
		<stats>
			<stat type="pAtk">489</stat>
			<stat type="mAtk">226</stat>
			<stat type="pAtkSpd">379</stat>
			<stat type="rCrit">8</stat>
			<stat type="randomDamage">10</stat>
			<stat type="pAtkRange">40</stat>
		</stats>
	</item>
	<item id="33755" name="테스트용 판타 무기 컬러베리" type="Weapon">
		<set name="icon" val="icon.weapon_estia_i00" />
		<set name="default_action" val="EQUIP" />
		<set name="bodypart" val="rhand" />
		<set name="weapon_type" val="SWORD" />
		<set name="crystal_type" val="R" />
		<set name="crystal_count" val="2902" />
		<set name="weight" val="1520" />
		<set name="price" val="136041000" />
		<set name="soulshots" val="1" />
		<set name="spiritshots" val="1" />
		<set name="enchant_enabled" val="true" />
		<set name="element_enabled" val="true" />
		<set name="commissionItemType" val="ONE_HAND_SWORD" />
		<set name="isAppearanceable" val="true" />
		<set name="damage_range" val="0;0;40;120" />
		<set name="immediate_effect" val="true" />
		<set name="material" val="STEEL" />
		<skills>
			<skill id="13252" level="3" type="ON_ENCHANT" type_value="4" /> 
		</skills>
		<stats>
			<stat type="pAtk">489</stat>
			<stat type="mAtk">226</stat>
			<stat type="pAtkSpd">379</stat>
			<stat type="rCrit">8</stat>
			<stat type="randomDamage">10</stat>
			<stat type="pAtkRange">40</stat>
		</stats>
	</item>
	<item id="33756" name="테스트용 헬리 무기 낡은것" type="Weapon">
		<set name="icon" val="icon.weapon_estia_i00" />
		<set name="default_action" val="EQUIP" />
		<set name="bodypart" val="rhand" />
		<set name="weapon_type" val="SWORD" />
		<set name="crystal_type" val="R" />
		<set name="crystal_count" val="2902" />
		<set name="weight" val="1520" />
		<set name="price" val="136041000" />
		<set name="soulshots" val="1" />
		<set name="spiritshots" val="1" />
		<set name="enchant_enabled" val="true" />
		<set name="element_enabled" val="true" />
		<set name="commissionItemType" val="ONE_HAND_SWORD" />
		<set name="isAppearanceable" val="true" />
		<set name="damage_range" val="0;0;40;120" />
		<set name="immediate_effect" val="true" />
		<set name="material" val="STEEL" />
		<skills>
			<skill id="13252" level="3" type="ON_ENCHANT" type_value="4" /> 
		</skills>
		<stats>
			<stat type="pAtk">489</stat>
			<stat type="mAtk">226</stat>
			<stat type="pAtkSpd">379</stat>
			<stat type="rCrit">8</stat>
			<stat type="randomDamage">10</stat>
			<stat type="pAtkRange">40</stat>
		</stats>
	</item>
	<item id="33757" name="테스트용 헬리 무기 컬러베리" type="Weapon">
		<set name="icon" val="icon.weapon_estia_i00" />
		<set name="default_action" val="EQUIP" />
		<set name="bodypart" val="rhand" />
		<set name="weapon_type" val="SWORD" />
		<set name="crystal_type" val="R" />
		<set name="crystal_count" val="2902" />
		<set name="weight" val="1520" />
		<set name="price" val="136041000" />
		<set name="soulshots" val="1" />
		<set name="spiritshots" val="1" />
		<set name="enchant_enabled" val="true" />
		<set name="element_enabled" val="true" />
		<set name="commissionItemType" val="ONE_HAND_SWORD" />
		<set name="isAppearanceable" val="true" />
		<set name="damage_range" val="0;0;40;120" />
		<set name="immediate_effect" val="true" />
		<set name="material" val="STEEL" />
		<skills>
			<skill id="13252" level="3" type="ON_ENCHANT" type_value="4" /> 
		</skills>
		<stats>
			<stat type="pAtk">489</stat>
			<stat type="mAtk">226</stat>
			<stat type="pAtkSpd">379</stat>
			<stat type="rCrit">8</stat>
			<stat type="randomDamage">10</stat>
			<stat type="pAtkRange">40</stat>
		</stats>
	</item>
	<item id="33758" name="테스트용 가즈 무기 낡은것" type="Weapon">
		<set name="icon" val="icon.weapon_estia_i00" />
		<set name="default_action" val="EQUIP" />
		<set name="bodypart" val="rhand" />
		<set name="weapon_type" val="SWORD" />
		<set name="crystal_type" val="R" />
		<set name="crystal_count" val="2902" />
		<set name="weight" val="1520" />
		<set name="price" val="136041000" />
		<set name="soulshots" val="1" />
		<set name="spiritshots" val="1" />
		<set name="enchant_enabled" val="true" />
		<set name="element_enabled" val="true" />
		<set name="commissionItemType" val="ONE_HAND_SWORD" />
		<set name="isAppearanceable" val="true" />
		<set name="damage_range" val="0;0;40;120" />
		<set name="immediate_effect" val="true" />
		<set name="material" val="STEEL" />
		<skills>
			<skill id="13252" level="3" type="ON_ENCHANT" type_value="4" /> 
		</skills>
		<stats>
			<stat type="pAtk">489</stat>
			<stat type="mAtk">226</stat>
			<stat type="pAtkSpd">379</stat>
			<stat type="rCrit">8</stat>
			<stat type="randomDamage">10</stat>
			<stat type="pAtkRange">40</stat>
		</stats>
	</item>
	<item id="33759" name="테스트용 가즈 무기 컬러베리" type="Weapon">
		<set name="icon" val="icon.weapon_estia_i00" />
		<set name="default_action" val="EQUIP" />
		<set name="bodypart" val="rhand" />
		<set name="weapon_type" val="SWORD" />
		<set name="crystal_type" val="R" />
		<set name="crystal_count" val="2902" />
		<set name="weight" val="1520" />
		<set name="price" val="136041000" />
		<set name="soulshots" val="1" />
		<set name="spiritshots" val="1" />
		<set name="enchant_enabled" val="true" />
		<set name="element_enabled" val="true" />
		<set name="commissionItemType" val="ONE_HAND_SWORD" />
		<set name="isAppearanceable" val="true" />
		<set name="damage_range" val="0;0;40;120" />
		<set name="immediate_effect" val="true" />
		<set name="material" val="STEEL" />
		<skills>
			<skill id="13252" level="3" type="ON_ENCHANT" type_value="4" /> 
		</skills>
		<stats>
			<stat type="pAtk">489</stat>
			<stat type="mAtk">226</stat>
			<stat type="pAtkSpd">379</stat>
			<stat type="rCrit">8</stat>
			<stat type="randomDamage">10</stat>
			<stat type="pAtkRange">40</stat>
		</stats>
	</item>
	<item id="33760" name="둠브링거의 힘이 봉인된 소드" type="Weapon">
		<set name="icon" val="icon.weapon_aseldor_i00" />
		<set name="weapon_type" val="SWORD" />
		<set name="is_tradable" val="false" />
		<set name="is_dropable" val="false" />
		<set name="is_destroyable" val="false" />
		<set name="is_sellable" val="false" />
		<set name="soulshots" val="6" />
		<set name="spiritshots" val="6" />
		<set name="bodypart" val="rhand" />
		<set name="is_oly_restricted" val="true" />
		<set name="isAppearanceable" val="true" />
		<set name="damage_range" val="0;0;40;120" />
		<set name="immediate_effect" val="true" />
		<set name="default_action" val="EQUIP" />
		<set name="material" val="STEEL" />
		<stats>
			<stat type="pAtk">30</stat>
			<stat type="mAtk">30</stat>
			<stat type="pAtkSpd">379</stat>
			<stat type="rCrit">8</stat>
			<stat type="randomDamage">10</stat>
			<stat type="pAtkRange">40</stat>
		</stats>
	</item>
	<item id="33761" name="소울하운드(남)의 힘이 봉인된 소드" type="Weapon">
		<set name="icon" val="icon.weapon_terakan_i00" />
		<set name="weapon_type" val="SWORD" />
		<set name="is_tradable" val="false" />
		<set name="is_dropable" val="false" />
		<set name="is_destroyable" val="false" />
		<set name="is_sellable" val="false" />
		<set name="soulshots" val="6" />
		<set name="spiritshots" val="6" />
		<set name="bodypart" val="rhand" />
		<set name="is_oly_restricted" val="true" />
		<set name="isAppearanceable" val="true" />
		<set name="damage_range" val="0;0;40;120" />
		<set name="immediate_effect" val="true" />
		<set name="default_action" val="EQUIP" />
		<set name="material" val="BRONZE" />
		<set name="is_magic_weapon" val="true" />
		<stats>
			<stat type="pAtk">30</stat>
			<stat type="mAtk">30</stat>
			<stat type="pAtkSpd">379</stat>
			<stat type="rCrit">8</stat>
			<stat type="randomDamage">10</stat>
			<stat type="pAtkRange">40</stat>
		</stats>
	</item>
	<item id="33762" name="소울하운드(여)의 힘이 봉인된 소드" type="Weapon">
		<set name="icon" val="icon.weapon_terakan_i00" />
		<set name="weapon_type" val="SWORD" />
		<set name="is_tradable" val="false" />
		<set name="is_dropable" val="false" />
		<set name="is_destroyable" val="false" />
		<set name="is_sellable" val="false" />
		<set name="soulshots" val="6" />
		<set name="spiritshots" val="6" />
		<set name="bodypart" val="rhand" />
		<set name="is_oly_restricted" val="true" />
		<set name="isAppearanceable" val="true" />
		<set name="damage_range" val="0;0;40;120" />
		<set name="immediate_effect" val="true" />
		<set name="default_action" val="EQUIP" />
		<set name="material" val="BRONZE" />
		<set name="is_magic_weapon" val="true" />
		<stats>
			<stat type="pAtk">30</stat>
			<stat type="mAtk">30</stat>
			<stat type="pAtkSpd">379</stat>
			<stat type="rCrit">8</stat>
			<stat type="randomDamage">10</stat>
			<stat type="pAtkRange">40</stat>
		</stats>
	</item>
	<item id="33763" name="트릭스터의 힘이 봉인된 크로스보우" type="Weapon">
		<set name="icon" val="icon.weapon_netra_i00" />
		<set name="weapon_type" val="CROSSBOW" />
		<set name="is_tradable" val="false" />
		<set name="is_dropable" val="false" />
		<set name="is_destroyable" val="false" />
		<set name="is_sellable" val="false" />
		<set name="soulshots" val="6" />
		<set name="spiritshots" val="6" />
		<set name="reuse_delay" val="400" />
		<set name="bodypart" val="lrhand" />
		<set name="is_oly_restricted" val="true" />
		<set name="isAppearanceable" val="true" />
		<set name="damage_range" val="0;0;40;120" />
		<set name="immediate_effect" val="true" />
		<set name="default_action" val="EQUIP" />
		<set name="material" val="STEEL" />
		<stats>
			<stat type="pAtk">30</stat>
			<stat type="mAtk">30</stat>
			<stat type="pAtkSpd">303</stat>
			<stat type="rCrit">10</stat>
			<stat type="randomDamage">10</stat>
			<stat type="accCombat">-1.5</stat>
			<stat type="pAtkRange">400</stat>
		</stats>
	</item>
	<item id="33764" name="내부 테스트용 소리수정" type="EtcItem">
		<set name="icon" val="icon.etc_echo_crystal_i00" />
		<set name="weight" val="10" />
		<set name="reuse_delay" val="20000" />
		<set name="commissionItemType" val="OTHER_ITEM" />
		<set name="default_action" val="SKILL_REDUCE" />
		<set name="handler" val="ItemSkills" />
		<set name="immediate_effect" val="true" />
		<set name="is_stackable" val="true" />
		<set name="material" val="PAPER" />
		<skills>
			<skill id="16032" level="1" /> 
		</skills>
	</item>
	<item id="33765" name="쥬디케이터의 힘이 봉인된 소드" type="Weapon">
		<set name="icon" val="icon.weapon_aseldor_i00" />
		<set name="weapon_type" val="SWORD" />
		<set name="is_tradable" val="false" />
		<set name="is_dropable" val="false" />
		<set name="is_destroyable" val="false" />
		<set name="is_sellable" val="false" />
		<set name="soulshots" val="6" />
		<set name="spiritshots" val="6" />
		<set name="bodypart" val="rhand" />
		<set name="is_oly_restricted" val="true" />
		<set name="isAppearanceable" val="true" />
		<set name="damage_range" val="0;0;40;120" />
		<set name="immediate_effect" val="true" />
		<set name="default_action" val="EQUIP" />
		<set name="material" val="STEEL" />
		<stats>
			<stat type="pAtk">30</stat>
			<stat type="mAtk">30</stat>
			<stat type="pAtkSpd">379</stat>
			<stat type="rCrit">8</stat>
			<stat type="randomDamage">10</stat>
			<stat type="pAtkRange">40</stat>
		</stats>
	</item>
	<item id="33766" name="축복의 비약" type="EtcItem">
		<set name="icon" val="icon.etc_super_potion_i03" />
		<set name="weight" val="5" />
		<set name="is_tradable" val="false" />
		<set name="is_dropable" val="false" />
		<set name="is_sellable" val="false" />
		<set name="crystal_type" val="R" />
		<set name="is_oly_restricted" val="true" />
		<set name="reuse_delay" val="120000" />
		<set name="shared_reuse_group" val="7" />
		<set name="default_action" val="SKILL_REDUCE" />
		<set name="etcitem_type" val="ELIXIR" />
		<set name="handler" val="ItemSkills" />
		<set name="immediate_effect" val="true" />
		<set name="is_stackable" val="true" />
		<set name="material" val="LIQUID" />
		<skills>
			<skill id="9219" level="1" /> 
			<skill id="9221" level="1" /> 
			<skill id="9222" level="1" /> 
			<skill id="9218" level="1" /> 
		</skills>
	</item>
	<item id="33767" name="R 탈리스만 - 인스턴트 킬 내성 {액티브}" type="Armor">
		<set name="icon" val="icon.r85_talisman_md_up_active" />
		<set name="default_action" val="EQUIP" />
		<set name="is_tradable" val="false" />
		<set name="is_dropable" val="false" />
		<set name="is_sellable" val="false" />
		<set name="bodypart" val="deco1" />
		<set name="useSkillDisTime" val="6" />
		<set name="duration" val="60" />
		<set name="immediate_effect" val="true" />
		<set name="weight" val="150" />
		<set name="material" val="GOLD" />
		<skills>
			<skill id="13350" level="1" /> 
		</skills>
	</item>
	<item id="33768" name="R 탈리스만 - 대미지 반사 내성 {액티브}" type="Armor">
		<set name="icon" val="icon.r85_talisman_md_up_active" />
		<set name="default_action" val="EQUIP" />
		<set name="is_tradable" val="false" />
		<set name="is_dropable" val="false" />
		<set name="is_sellable" val="false" />
		<set name="bodypart" val="deco1" />
		<set name="useSkillDisTime" val="6" />
		<set name="duration" val="60" />
		<set name="immediate_effect" val="true" />
		<set name="weight" val="150" />
		<set name="material" val="GOLD" />
		<skills>
			<skill id="13349" level="1" /> 
		</skills>
	</item>
	<item id="33769" name="R 탈리스만 - 인스턴트 킬 내성 {액티브}" type="Armor">
		<set name="icon" val="icon.r85_talisman_md_up_active" />
		<set name="default_action" val="EQUIP" />
		<set name="is_tradable" val="false" />
		<set name="is_dropable" val="false" />
		<set name="is_sellable" val="false" />
		<set name="bodypart" val="deco1" />
		<set name="useSkillDisTime" val="6" />
		<set name="duration" val="600" />
		<set name="immediate_effect" val="true" />
		<set name="weight" val="150" />
		<set name="material" val="GOLD" />
		<skills>
			<skill id="13350" level="1" /> 
		</skills>
	</item>
	<item id="33770" name="R 탈리스만 - 대미지 반사 내성 {액티브}" type="Armor">
		<set name="icon" val="icon.r85_talisman_md_up_active" />
		<set name="default_action" val="EQUIP" />
		<set name="is_tradable" val="false" />
		<set name="is_dropable" val="false" />
		<set name="is_sellable" val="false" />
		<set name="bodypart" val="deco1" />
		<set name="useSkillDisTime" val="6" />
		<set name="duration" val="600" />
		<set name="immediate_effect" val="true" />
		<set name="weight" val="150" />
		<set name="material" val="GOLD" />
		<skills>
			<skill id="13349" level="1" /> 
		</skills>
	</item>
	<item id="33771" name="아덴 영웅의 보상 상자" type="EtcItem">
		<set name="icon" val="icon.etc_pi_gift_box_i00" />
		<set name="weight" val="100" />
		<set name="is_tradable" val="false" />
		<set name="is_dropable" val="false" />
		<set name="is_sellable" val="false" />
		<set name="is_oly_restricted" val="true" />
		<set name="default_action" val="PEEL" />
		<set name="immediate_effect" val="true" />
		<set name="is_stackable" val="true" />
		<set name="handler" val="ExtractableItems" />
		<set name="material" val="FISH" />
		<capsuled_items>
			<item id="9570" min="1" max="1" chance="100" /> 
			<item id="57" min="5000000" max="5000000" chance="100" /> 
			<item id="6622" min="1" max="1" chance="100" /> 
		</capsuled_items>
	</item>
	<item id="33772" name="아덴 영웅의 보상 상자" type="EtcItem">
		<set name="icon" val="icon.etc_pi_gift_box_i00" />
		<set name="weight" val="100" />
		<set name="is_tradable" val="false" />
		<set name="is_dropable" val="false" />
		<set name="is_sellable" val="false" />
		<set name="is_oly_restricted" val="true" />
		<set name="default_action" val="PEEL" />
		<set name="immediate_effect" val="true" />
		<set name="is_stackable" val="true" />
		<set name="handler" val="ExtractableItems" />
		<set name="material" val="FISH" />
		<capsuled_items>
			<item id="9571" min="1" max="1" chance="100" /> 
			<item id="57" min="5000000" max="5000000" chance="100" /> 
			<item id="6622" min="1" max="1" chance="100" /> 
		</capsuled_items>
	</item>
	<item id="33773" name="아덴 영웅의 보상 상자" type="EtcItem">
		<set name="icon" val="icon.etc_pi_gift_box_i00" />
		<set name="weight" val="100" />
		<set name="is_tradable" val="false" />
		<set name="is_dropable" val="false" />
		<set name="is_sellable" val="false" />
		<set name="is_oly_restricted" val="true" />
		<set name="default_action" val="PEEL" />
		<set name="immediate_effect" val="true" />
		<set name="is_stackable" val="true" />
		<set name="handler" val="ExtractableItems" />
		<set name="material" val="FISH" />
		<capsuled_items>
			<item id="9572" min="1" max="1" chance="100" /> 
			<item id="57" min="5000000" max="5000000" chance="100" /> 
			<item id="6622" min="1" max="1" chance="100" /> 
		</capsuled_items>
	</item>
	<item id="33774" name="무급 정령탄" additionalName="이벤트" type="EtcItem">
		<set name="icon" val="icon.etc_spirit_bullet_white_i00" />
		<set name="is_tradable" val="false" />
		<set name="is_dropable" val="false" />
		<set name="is_sellable" val="false" />
		<set name="default_action" val="SOULSHOT" />
		<set name="etcitem_type" val="SOULSHOT" />
		<set name="immediate_effect" val="true" />
		<set name="is_stackable" val="true" />
		<set name="handler" val="SoulShots" />
		<set name="material" val="PAPER" />
		<skills>
			<skill id="2039" level="1" /> 
		</skills>
	</item>
	<item id="33775" name="정령탄 - D그레이드" additionalName="이벤트" type="EtcItem">
		<set name="icon" val="icon.etc_spirit_bullet_blue_i00" />
		<set name="is_tradable" val="false" />
		<set name="is_dropable" val="false" />
		<set name="is_sellable" val="false" />
		<set name="crystal_type" val="D" />
		<set name="default_action" val="SOULSHOT" />
		<set name="etcitem_type" val="SOULSHOT" />
		<set name="immediate_effect" val="true" />
		<set name="is_stackable" val="true" />
		<set name="handler" val="SoulShots" />
		<set name="material" val="PAPER" />
		<skills>
			<skill id="2150" level="1" /> 
		</skills>
	</item>
	<item id="33776" name="정령탄 - C그레이드" additionalName="이벤트" type="EtcItem">
		<set name="icon" val="icon.etc_spirit_bullet_green_i00" />
		<set name="is_tradable" val="false" />
		<set name="is_dropable" val="false" />
		<set name="is_sellable" val="false" />
		<set name="crystal_type" val="C" />
		<set name="default_action" val="SOULSHOT" />
		<set name="etcitem_type" val="SOULSHOT" />
		<set name="immediate_effect" val="true" />
		<set name="is_stackable" val="true" />
		<set name="handler" val="SoulShots" />
		<set name="material" val="PAPER" />
		<skills>
			<skill id="2151" level="1" /> 
		</skills>
	</item>
	<item id="33777" name="정령탄 - B그레이드" additionalName="이벤트" type="EtcItem">
		<set name="icon" val="icon.etc_spirit_bullet_red_i00" />
		<set name="is_tradable" val="false" />
		<set name="is_dropable" val="false" />
		<set name="is_sellable" val="false" />
		<set name="crystal_type" val="B" />
		<set name="default_action" val="SOULSHOT" />
		<set name="etcitem_type" val="SOULSHOT" />
		<set name="immediate_effect" val="true" />
		<set name="is_stackable" val="true" />
		<set name="handler" val="SoulShots" />
		<set name="material" val="PAPER" />
		<skills>
			<skill id="2152" level="1" /> 
		</skills>
	</item>
	<item id="33778" name="정령탄 - A그레이드" additionalName="이벤트" type="EtcItem">
		<set name="icon" val="icon.etc_spirit_bullet_silver_i00" />
		<set name="is_tradable" val="false" />
		<set name="is_dropable" val="false" />
		<set name="is_sellable" val="false" />
		<set name="crystal_type" val="A" />
		<set name="default_action" val="SOULSHOT" />
		<set name="etcitem_type" val="SOULSHOT" />
		<set name="immediate_effect" val="true" />
		<set name="is_stackable" val="true" />
		<set name="handler" val="SoulShots" />
		<set name="material" val="PAPER" />
		<skills>
			<skill id="2153" level="1" /> 
		</skills>
	</item>
	<item id="33779" name="정령탄 - S그레이드" additionalName="이벤트" type="EtcItem">
		<set name="icon" val="icon.etc_spirit_bullet_gold_i00" />
		<set name="is_tradable" val="false" />
		<set name="is_dropable" val="false" />
		<set name="is_sellable" val="false" />
		<set name="crystal_type" val="S" />
		<set name="default_action" val="SOULSHOT" />
		<set name="etcitem_type" val="SOULSHOT" />
		<set name="immediate_effect" val="true" />
		<set name="is_stackable" val="true" />
		<set name="handler" val="SoulShots" />
		<set name="material" val="PAPER" />
		<skills>
			<skill id="2154" level="1" /> 
		</skills>
	</item>
	<item id="33780" name="정령탄 - R그레이드" additionalName="이벤트" type="EtcItem">
		<set name="icon" val="icon.soulshot_r_i00" />
		<set name="is_tradable" val="false" />
		<set name="is_dropable" val="false" />
		<set name="is_sellable" val="false" />
		<set name="crystal_type" val="R" />
		<set name="material" val="PAPER" />
		<set name="handler" val="SoulShots" />
		<set name="default_action" val="SOULSHOT" />
		<set name="etcitem_type" val="SOULSHOT" />
		<set name="immediate_effect" val="true" />
		<set name="is_stackable" val="true" />
		<set name="handler" val="SoulShots" />
		<skills>
			<skill id="9193" level="1" /> 
		</skills>
	</item>
	<item id="33781" name="무급 마정탄" additionalName="이벤트" type="EtcItem">
		<set name="icon" val="icon.etc_spell_shot_white_i00" />
		<set name="is_tradable" val="false" />
		<set name="is_dropable" val="false" />
		<set name="is_sellable" val="false" />
		<set name="default_action" val="SPIRITSHOT" />
		<set name="etcitem_type" val="SOULSHOT" />
		<set name="immediate_effect" val="true" />
		<set name="is_stackable" val="true" />
		<set name="handler" val="SpiritShot" />
		<set name="material" val="PAPER" />
		<skills>
			<skill id="2047" level="1" /> 
		</skills>
	</item>
	<item id="33782" name="마정탄 - D그레이드" additionalName="이벤트" type="EtcItem">
		<set name="icon" val="icon.etc_spell_shot_blue_i00" />
		<set name="is_tradable" val="false" />
		<set name="is_dropable" val="false" />
		<set name="is_sellable" val="false" />
		<set name="crystal_type" val="D" />
		<set name="default_action" val="SPIRITSHOT" />
		<set name="etcitem_type" val="SOULSHOT" />
		<set name="immediate_effect" val="true" />
		<set name="is_stackable" val="true" />
		<set name="handler" val="SpiritShot" />
		<set name="material" val="PAPER" />
		<skills>
			<skill id="2155" level="1" /> 
		</skills>
	</item>
	<item id="33783" name="마정탄 - C그레이드" additionalName="이벤트" type="EtcItem">
		<set name="icon" val="icon.etc_spell_shot_green_i00" />
		<set name="is_tradable" val="false" />
		<set name="is_dropable" val="false" />
		<set name="is_sellable" val="false" />
		<set name="crystal_type" val="C" />
		<set name="default_action" val="SPIRITSHOT" />
		<set name="etcitem_type" val="SOULSHOT" />
		<set name="immediate_effect" val="true" />
		<set name="is_stackable" val="true" />
		<set name="handler" val="SpiritShot" />
		<set name="material" val="PAPER" />
		<skills>
			<skill id="2156" level="1" /> 
		</skills>
	</item>
	<item id="33784" name="마정탄 - B그레이드" additionalName="이벤트" type="EtcItem">
		<set name="icon" val="icon.etc_spell_shot_red_i00" />
		<set name="is_tradable" val="false" />
		<set name="is_dropable" val="false" />
		<set name="is_sellable" val="false" />
		<set name="crystal_type" val="B" />
		<set name="default_action" val="SPIRITSHOT" />
		<set name="etcitem_type" val="SOULSHOT" />
		<set name="immediate_effect" val="true" />
		<set name="is_stackable" val="true" />
		<set name="handler" val="SpiritShot" />
		<set name="material" val="PAPER" />
		<skills>
			<skill id="2157" level="1" /> 
		</skills>
	</item>
	<item id="33785" name="마정탄 - A그레이드" additionalName="이벤트" type="EtcItem">
		<set name="icon" val="icon.etc_spell_shot_silver_i00" />
		<set name="is_tradable" val="false" />
		<set name="is_dropable" val="false" />
		<set name="is_sellable" val="false" />
		<set name="crystal_type" val="A" />
		<set name="default_action" val="SPIRITSHOT" />
		<set name="etcitem_type" val="SOULSHOT" />
		<set name="immediate_effect" val="true" />
		<set name="is_stackable" val="true" />
		<set name="handler" val="SpiritShot" />
		<set name="material" val="PAPER" />
		<skills>
			<skill id="2158" level="1" /> 
		</skills>
	</item>
	<item id="33786" name="마정탄 - S그레이드" additionalName="이벤트" type="EtcItem">
		<set name="icon" val="icon.etc_spell_shot_gold_i00" />
		<set name="is_tradable" val="false" />
		<set name="is_dropable" val="false" />
		<set name="is_sellable" val="false" />
		<set name="crystal_type" val="S" />
		<set name="default_action" val="SPIRITSHOT" />
		<set name="etcitem_type" val="SOULSHOT" />
		<set name="immediate_effect" val="true" />
		<set name="is_stackable" val="true" />
		<set name="handler" val="SpiritShot" />
		<set name="material" val="PAPER" />
		<skills>
			<skill id="2159" level="1" /> 
		</skills>
	</item>
	<item id="33787" name="마정탄 - R그레이드" additionalName="이벤트" type="EtcItem">
		<set name="icon" val="icon.spiritshot_r_i00" />
		<set name="is_tradable" val="false" />
		<set name="is_dropable" val="false" />
		<set name="is_sellable" val="false" />
		<set name="crystal_type" val="R" />
		<set name="default_action" val="SPIRITSHOT" />
		<set name="etcitem_type" val="SOULSHOT" />
		<set name="immediate_effect" val="true" />
		<set name="is_stackable" val="true" />
		<set name="handler" val="SpiritShot" />
		<set name="material" val="PAPER" />
		<skills>
			<skill id="9194" level="1" /> 
		</skills>
	</item>
	<item id="33788" name="축복받은 무급 마정탄" additionalName="이벤트" type="EtcItem">
		<set name="icon" val="icon.etc_spell_shot_white_i01" />
		<set name="is_tradable" val="false" />
		<set name="is_dropable" val="false" />
		<set name="is_sellable" val="false" />
		<set name="default_action" val="SPIRITSHOT" />
		<set name="etcitem_type" val="SOULSHOT" />
		<set name="immediate_effect" val="true" />
		<set name="is_stackable" val="true" />
		<set name="handler" val="BlessedSpiritShot" />
		<set name="material" val="PAPER" />
		<skills>
			<skill id="2061" level="1" /> 
		</skills>
	</item>
	<item id="33789" name="축복받은 마정탄 - D그레이드" additionalName="이벤트" type="EtcItem">
		<set name="icon" val="icon.etc_spell_shot_blue_i01" />
		<set name="is_tradable" val="false" />
		<set name="is_dropable" val="false" />
		<set name="is_sellable" val="false" />
		<set name="crystal_type" val="D" />
		<set name="default_action" val="SPIRITSHOT" />
		<set name="etcitem_type" val="SOULSHOT" />
		<set name="immediate_effect" val="true" />
		<set name="is_stackable" val="true" />
		<set name="handler" val="BlessedSpiritShot" />
		<set name="material" val="PAPER" />
		<skills>
			<skill id="2160" level="1" /> 
		</skills>
	</item>
	<item id="33790" name="축복받은 마정탄 - C그레이드" additionalName="이벤트" type="EtcItem">
		<set name="icon" val="icon.etc_spell_shot_green_i01" />
		<set name="is_tradable" val="false" />
		<set name="is_dropable" val="false" />
		<set name="is_sellable" val="false" />
		<set name="crystal_type" val="C" />
		<set name="default_action" val="SPIRITSHOT" />
		<set name="etcitem_type" val="SOULSHOT" />
		<set name="immediate_effect" val="true" />
		<set name="is_stackable" val="true" />
		<set name="handler" val="BlessedSpiritShot" />
		<set name="material" val="PAPER" />
		<skills>
			<skill id="2161" level="1" /> 
		</skills>
	</item>
	<item id="33791" name="축복받은 마정탄 - B그레이드" additionalName="이벤트" type="EtcItem">
		<set name="icon" val="icon.etc_spell_shot_red_i01" />
		<set name="is_tradable" val="false" />
		<set name="is_dropable" val="false" />
		<set name="is_sellable" val="false" />
		<set name="crystal_type" val="B" />
		<set name="default_action" val="SPIRITSHOT" />
		<set name="etcitem_type" val="SOULSHOT" />
		<set name="immediate_effect" val="true" />
		<set name="is_stackable" val="true" />
		<set name="handler" val="BlessedSpiritShot" />
		<set name="material" val="PAPER" />
		<skills>
			<skill id="2162" level="1" /> 
		</skills>
	</item>
	<item id="33792" name="축복받은 마정탄 - A그레이드" additionalName="이벤트" type="EtcItem">
		<set name="icon" val="icon.etc_spell_shot_silver_i01" />
		<set name="is_tradable" val="false" />
		<set name="is_dropable" val="false" />
		<set name="is_sellable" val="false" />
		<set name="crystal_type" val="A" />
		<set name="default_action" val="SPIRITSHOT" />
		<set name="etcitem_type" val="SOULSHOT" />
		<set name="immediate_effect" val="true" />
		<set name="is_stackable" val="true" />
		<set name="handler" val="BlessedSpiritShot" />
		<set name="material" val="PAPER" />
		<skills>
			<skill id="2163" level="1" /> 
		</skills>
	</item>
	<item id="33793" name="축복받은 마정탄 - S그레이드" additionalName="이벤트" type="EtcItem">
		<set name="icon" val="icon.etc_spell_shot_gold_i01" />
		<set name="is_tradable" val="false" />
		<set name="is_dropable" val="false" />
		<set name="is_sellable" val="false" />
		<set name="crystal_type" val="S" />
		<set name="default_action" val="SPIRITSHOT" />
		<set name="etcitem_type" val="SOULSHOT" />
		<set name="immediate_effect" val="true" />
		<set name="is_stackable" val="true" />
		<set name="handler" val="BlessedSpiritShot" />
		<set name="material" val="PAPER" />
		<skills>
			<skill id="2164" level="1" /> 
		</skills>
	</item>
	<item id="33794" name="축복받은 마정탄 - R그레이드" additionalName="이벤트" type="EtcItem">
		<set name="icon" val="icon.blessed_spiritshot_r_i00" />
		<set name="is_tradable" val="false" />
		<set name="is_dropable" val="false" />
		<set name="is_sellable" val="false" />
		<set name="crystal_type" val="R" />
		<set name="default_action" val="SPIRITSHOT" />
		<set name="etcitem_type" val="SOULSHOT" />
		<set name="immediate_effect" val="true" />
		<set name="is_stackable" val="true" />
		<set name="handler" val="BlessedSpiritShot" />
		<set name="material" val="PAPER" />
		<skills>
			<skill id="9195" level="1" /> 
		</skills>
	</item>
	<item id="33795" name="귀환 영웅의 활력 회복 음료 3개 팩" additionalName="이벤트" type="EtcItem">
		<set name="icon" val="icon.etc_pi_gift_box_i00" />
		<set name="weight" val="100" />
		<set name="is_tradable" val="false" />
		<set name="is_dropable" val="false" />
		<set name="is_sellable" val="false" />
		<set name="is_freightable" val="true" />
		<set name="default_action" val="PEEL" />
		<set name="immediate_effect" val="true" />
		<set name="is_stackable" val="true" />
		<set name="handler" val="ExtractableItems" />
		<set name="material" val="FISH" />
		<capsuled_items>
			<item id="33512" min="3" max="3" chance="100" /> 
		</capsuled_items>
	</item>
	<item id="33796" name="귀환 영웅의 황금상자" additionalName="이벤트" type="EtcItem">
		<set name="icon" val="icon.present_of_destination_event" />
		<set name="weight" val="100" />
		<set name="is_tradable" val="false" />
		<set name="is_dropable" val="false" />
		<set name="is_sellable" val="false" />
		<set name="is_oly_restricted" val="true" />
		<set name="is_freightable" val="true" />
		<set name="default_action" val="PEEL" />
		<set name="immediate_effect" val="true" />
		<set name="is_stackable" val="true" />
		<set name="handler" val="ExtractableItems" />
		<set name="material" val="FISH" />
		<capsuled_items>
			<item id="33511" min="250" max="250" chance="100" /> 
			<item id="36021" min="1" max="1" chance="100" /> 
			<item id="36023" min="1" max="1" chance="100" /> 
		</capsuled_items>
	</item>
	<item id="33797" name="아가시온 봉인 팔찌 - 테르시의 빛" additionalName="이벤트" type="Armor">
		<set name="icon" val="icon.bracelet_tersi_agathion" />
		<set name="default_action" val="EQUIP" />
		<set name="is_tradable" val="false" />
		<set name="is_dropable" val="false" />
		<set name="is_sellable" val="false" />
		<set name="bodypart" val="lbracelet" />
		<set name="is_oly_restricted" val="true" />
		<set name="immediate_effect" val="true" />
		<set name="weight" val="150" />
		<set name="material" val="SILVER" />
		<skills>
			<skill id="13345" level="1" /> 
			<skill id="13346" level="1" /> 
			<skill id="13347" level="1" /> 
			<skill id="3267" level="1" type="ON_UNEQUIP" /> 
		</skills>
	</item>
	<item id="33798" name="빛의 환영" additionalName="이벤트" type="EtcItem">
		<set name="icon" val="icon.tersi_specter_seed" />
		<set name="is_sellable" val="false" />
		<set name="is_oly_restricted" val="true" />
		<set name="reuse_delay" val="10000" />
		<set name="default_action" val="SKILL_REDUCE" />
		<set name="etcitem_type" val="SCROLL" />
		<set name="handler" val="ItemSkills" />
		<set name="immediate_effect" val="true" />
		<set name="is_stackable" val="true" />
		<set name="material" val="PAPER" />
		<skills>
			<skill id="9225" level="1" /> 
		</skills>
	</item>
	<item id="33799" name="빛의 조각" additionalName="이벤트" type="EtcItem">
		<set name="icon" val="icon.tersi_light_gragment" />
		<set name="is_sellable" val="false" />
		<set name="is_oly_restricted" val="true" />
		<set name="reuse_delay" val="10000" />
		<set name="default_action" val="SKILL_REDUCE" />
		<set name="etcitem_type" val="SCROLL" />
		<set name="handler" val="ItemSkills" />
		<set name="is_stackable" val="true" />
		<set name="material" val="PAPER" />
		<skills>
			<skill id="9226" level="1" /> 
		</skills>
	</item>
</list>