<?xml version="1.0" encoding="UTF-8"?>
<list isChanceMultisell="true" xmlns:xsi="http://www.w3.org/2001/XMLSchema-instance" xsi:noNamespaceSchemaLocation="../../xsd/multisell.xsd">
	<npcs>
		<npc>32478</npc> <!-- S80 상급 무기 -->
	</npcs>
	<item>
		<ingredient id="57" count="60000000" /> <!-- 아데나 -->
		<ingredient id="36549" count="28" /> <!-- 상급 무기 조각 -->
		<ingredient id="1877" count="420" /> <!-- 아다만타이트 -->
		<ingredient id="1893" count="1350" /> <!-- 오리하루콘 -->
		<ingredient id="4042" count="250" /> <!-- 엔리아 -->
		<ingredient id="1888" count="310" /> <!-- 합성 코크스 -->
		<ingredient id="2134" count="39" /> <!-- 젬스톤 S 그레이드 -->
		<ingredient id="1462" count="675" /> <!-- 결정체 S 그레이드 -->
		<production id="15558" count="1" chance="10" /> <!-- 페리 엘 소드 -->
		<production id="15558" count="1" chance="50" /> <!-- 페리 엘 소드 -->
	</item>
	<item>
		<ingredient id="57" count="60000000" /> <!-- 아데나 -->
		<ingredient id="36549" count="28" /> <!-- 상급 무기 조각 -->
		<ingredient id="1877" count="420" /> <!-- 아다만타이트 -->
		<ingredient id="1893" count="1350" /> <!-- 오리하루콘 -->
		<ingredient id="4042" count="250" /> <!-- 엔리아 -->
		<ingredient id="1888" count="310" /> <!-- 합성 코크스 -->
		<ingredient id="2134" count="39" /> <!-- 젬스톤 S 그레이드 -->
		<ingredient id="1462" count="675" /> <!-- 결정체 S 그레이드 -->
		<production id="15559" count="1" chance="10" /> <!-- 스컬 엣지 -->
		<production id="15559" count="1" chance="50" /> <!-- 스컬 엣지 -->
	</item>
	<item>
		<ingredient id="57" count="60000000" /> <!-- 아데나 -->
		<ingredient id="36549" count="28" /> <!-- 상급 무기 조각 -->
		<ingredient id="1877" count="420" /> <!-- 아다만타이트 -->
		<ingredient id="1893" count="1350" /> <!-- 오리하루콘 -->
		<ingredient id="4042" count="250" /> <!-- 엔리아 -->
		<ingredient id="1888" count="310" /> <!-- 합성 코크스 -->
		<ingredient id="2134" count="39" /> <!-- 젬스톤 S 그레이드 -->
		<ingredient id="1462" count="675" /> <!-- 결정체 S 그레이드 -->
		<production id="15560" count="1" chance="10" /> <!-- 비그위크 액스 -->
		<production id="15560" count="1" chance="50" /> <!-- 비그위크 액스 -->
	</item>
	<item>
		<ingredient id="57" count="60000000" /> <!-- 아데나 -->
		<ingredient id="36549" count="28" /> <!-- 상급 무기 조각 -->
		<ingredient id="1877" count="420" /> <!-- 아다만타이트 -->
		<ingredient id="1893" count="1350" /> <!-- 오리하루콘 -->
		<ingredient id="4042" count="250" /> <!-- 엔리아 -->
		<ingredient id="1888" count="310" /> <!-- 합성 코크스 -->
		<ingredient id="2134" count="39" /> <!-- 젬스톤 S 그레이드 -->
		<ingredient id="1462" count="675" /> <!-- 결정체 S 그레이드 -->
		<production id="15561" count="1" chance="10" /> <!-- 이블디어티 마울 -->
		<production id="15561" count="1" chance="50" /> <!-- 이블디어티 마울 -->
	</item>
	<item>
		<ingredient id="57" count="60000000" /> <!-- 아데나 -->
		<ingredient id="36549" count="28" /> <!-- 상급 무기 조각 -->
		<ingredient id="1877" count="420" /> <!-- 아다만타이트 -->
		<ingredient id="1893" count="1350" /> <!-- 오리하루콘 -->
		<ingredient id="4042" count="250" /> <!-- 엔리아 -->
		<ingredient id="1888" count="310" /> <!-- 합성 코크스 -->
		<ingredient id="2134" count="39" /> <!-- 젬스톤 S 그레이드 -->
		<ingredient id="1462" count="675" /> <!-- 결정체 S 그레이드 -->
		<production id="15562" count="1" chance="10" /> <!-- 페더아이 블레이드 -->
		<production id="15562" count="1" chance="50" /> <!-- 페더아이 블레이드 -->
	</item>
	<item>
		<ingredient id="57" count="60000000" /> <!-- 아데나 -->
		<ingredient id="36549" count="28" /> <!-- 상급 무기 조각 -->
		<ingredient id="1877" count="420" /> <!-- 아다만타이트 -->
		<ingredient id="1893" count="1350" /> <!-- 오리하루콘 -->
		<ingredient id="4042" count="250" /> <!-- 엔리아 -->
		<ingredient id="1888" count="310" /> <!-- 합성 코크스 -->
		<ingredient id="2134" count="39" /> <!-- 젬스톤 S 그레이드 -->
		<ingredient id="1462" count="675" /> <!-- 결정체 S 그레이드 -->
		<production id="15563" count="1" chance="10" /> <!-- 옥토 클로 -->
		<production id="15563" count="1" chance="50" /> <!-- 옥토 클로 -->
	</item>
	<item>
		<ingredient id="57" count="60000000" /> <!-- 아데나 -->
		<ingredient id="36549" count="28" /> <!-- 상급 무기 조각 -->
		<ingredient id="1877" count="420" /> <!-- 아다만타이트 -->
		<ingredient id="1893" count="1350" /> <!-- 오리하루콘 -->
		<ingredient id="4042" count="250" /> <!-- 엔리아 -->
		<ingredient id="1888" count="310" /> <!-- 합성 코크스 -->
		<ingredient id="2134" count="39" /> <!-- 젬스톤 S 그레이드 -->
		<ingredient id="1462" count="675" /> <!-- 결정체 S 그레이드 -->
		<production id="15564" count="1" chance="10" /> <!-- 더블토파 스피어 -->
		<production id="15564" count="1" chance="50" /> <!-- 더블토파 스피어 -->
	</item>
	<item>
		<ingredient id="57" count="60000000" /> <!-- 아데나 -->
		<ingredient id="36549" count="28" /> <!-- 상급 무기 조각 -->
		<ingredient id="1877" count="420" /> <!-- 아다만타이트 -->
		<ingredient id="1893" count="1350" /> <!-- 오리하루콘 -->
		<ingredient id="4042" count="250" /> <!-- 엔리아 -->
		<ingredient id="1888" count="310" /> <!-- 합성 코크스 -->
		<ingredient id="2134" count="39" /> <!-- 젬스톤 S 그레이드 -->
		<ingredient id="1462" count="675" /> <!-- 결정체 S 그레이드 -->
		<production id="15565" count="1" chance="10" /> <!-- 큐티클 -->
		<production id="15565" count="1" chance="50" /> <!-- 큐티클 -->
	</item>
	<item>
		<ingredient id="57" count="60000000" /> <!-- 아데나 -->
		<ingredient id="36549" count="28" /> <!-- 상급 무기 조각 -->
		<ingredient id="1877" count="420" /> <!-- 아다만타이트 -->
		<ingredient id="1893" count="1350" /> <!-- 오리하루콘 -->
		<ingredient id="4042" count="250" /> <!-- 엔리아 -->
		<ingredient id="1888" count="310" /> <!-- 합성 코크스 -->
		<ingredient id="2134" count="39" /> <!-- 젬스톤 S 그레이드 -->
		<ingredient id="1462" count="675" /> <!-- 결정체 S 그레이드 -->
		<production id="15566" count="1" chance="10" /> <!-- 블랙비지즈 -->
		<production id="15566" count="1" chance="50" /> <!-- 블랙비지즈 -->
	</item>
	<item>
		<ingredient id="57" count="60000000" /> <!-- 아데나 -->
		<ingredient id="36549" count="28" /> <!-- 상급 무기 조각 -->
		<ingredient id="1877" count="420" /> <!-- 아다만타이트 -->
		<ingredient id="1893" count="1350" /> <!-- 오리하루콘 -->
		<ingredient id="4042" count="250" /> <!-- 엔리아 -->
		<ingredient id="1888" count="310" /> <!-- 합성 코크스 -->
		<ingredient id="2134" count="39" /> <!-- 젬스톤 S 그레이드 -->
		<ingredient id="1462" count="675" /> <!-- 결정체 S 그레이드 -->
		<production id="15567" count="1" chance="10" /> <!-- 베니플렌트 소드 -->
		<production id="15567" count="1" chance="50" /> <!-- 베니플렌트 소드 -->
	</item>
	<item>
		<ingredient id="57" count="60000000" /> <!-- 아데나 -->
		<ingredient id="36549" count="28" /> <!-- 상급 무기 조각 -->
		<ingredient id="1877" count="420" /> <!-- 아다만타이트 -->
		<ingredient id="1893" count="1350" /> <!-- 오리하루콘 -->
		<ingredient id="4042" count="250" /> <!-- 엔리아 -->
		<ingredient id="1888" count="310" /> <!-- 합성 코크스 -->
		<ingredient id="2134" count="39" /> <!-- 젬스톤 S 그레이드 -->
		<ingredient id="1462" count="675" /> <!-- 결정체 S 그레이드 -->
		<production id="15568" count="1" chance="10" /> <!-- 스컬 카르니움 보우 -->
		<production id="15568" count="1" chance="50" /> <!-- 스컬 카르니움 보우 -->
	</item>
</list>
